b'<?xml version="1.0" ?>\n<!DOCTYPE PubmedArticleSet PUBLIC "-//NLM//DTD PubMedArticle, 1st January 2023//EN" "https://dtd.nlm.nih.gov/ncbi/pubmed/out/pubmed_230101.dtd">\n<PubmedArticleSet>\n<PubmedArticle><MedlineCitation Status="MEDLINE" Owner="NLM"><PMID Version="1">10195063</PMID><DateCompleted><Year>1999</Year><Month>04</Month><Day>20</Day></DateCompleted><DateRevised><Year>2022</Year><Month>12</Month><Day>07</Day></DateRevised><Article PubModel="Print"><Journal><ISSN IssnType="Print">1368-4973</ISSN><JournalIssue CitedMedium="Print"><Volume>74</Volume><Issue>6</Issue><PubDate><Year>1998</Year><Month>Dec</Month></PubDate></JournalIssue><Title>Sexually transmitted infections</Title><ISOAbbreviation>Sex Transm Infect</ISOAbbreviation></Journal><ArticleTitle>The case against routine HPV testing in cervical screening.</ArticleTitle><Pagination><StartPage>457</StartPage><MedlinePgn>457</MedlinePgn></Pagination><AuthorList CompleteYN="Y"><Author ValidYN="Y"><LastName>Duncan</LastName><ForeName>I</ForeName><Initials>I</Initials></Author></AuthorList><Language>eng</Language><PublicationTypeList><PublicationType UI="D016422">Letter</PublicationType></PublicationTypeList></Article><MedlineJournalInfo><Country>England</Country><MedlineTA>Sex Transm Infect</MedlineTA><NlmUniqueID>9805554</NlmUniqueID><ISSNLinking>1368-4973</ISSNLinking></MedlineJournalInfo><CitationSubset>IM</CitationSubset><MeshHeadingList><MeshHeading><DescriptorName UI="D000328" MajorTopicYN="N">Adult</DescriptorName></MeshHeading><MeshHeading><DescriptorName UI="D005260" MajorTopicYN="N">Female</DescriptorName></MeshHeading><MeshHeading><DescriptorName UI="D006801" MajorTopicYN="N">Humans</DescriptorName></MeshHeading><MeshHeading><DescriptorName UI="D008403" MajorTopicYN="N">Mass Screening</DescriptorName><QualifierName UI="Q000379" MajorTopicYN="N">methods</QualifierName></MeshHeading><MeshHeading><DescriptorName UI="D008875" MajorTopicYN="N">Middle Aged</DescriptorName></MeshHeading><MeshHeading><DescriptorName UI="D030361" MajorTopicYN="N">Papillomavirus Infections</DescriptorName><QualifierName UI="Q000175" MajorTopicYN="Y">diagnosis</QualifierName></MeshHeading><MeshHeading><DescriptorName UI="D012680" MajorTopicYN="N">Sensitivity and Specificity</DescriptorName></MeshHeading><MeshHeading><DescriptorName UI="D006113" MajorTopicYN="N">United Kingdom</DescriptorName></MeshHeading><MeshHeading><DescriptorName UI="D002583" MajorTopicYN="N">Uterine Cervical Neoplasms</DescriptorName><QualifierName UI="Q000517" MajorTopicYN="Y">prevention &amp; control</QualifierName><QualifierName UI="Q000821" MajorTopicYN="N">virology</QualifierName></MeshHeading><MeshHeading><DescriptorName UI="D002578" MajorTopicYN="N">Uterine Cervical Dysplasia</DescriptorName><QualifierName UI="Q000517" MajorTopicYN="Y">prevention &amp; control</QualifierName><QualifierName UI="Q000821" MajorTopicYN="N">virology</QualifierName></MeshHeading></MeshHeadingList></MedlineCitation><PubmedData><History><PubMedPubDate PubStatus="pubmed"><Year>1999</Year><Month>4</Month><Day>9</Day></PubMedPubDate><PubMedPubDate PubStatus="medline"><Year>1999</Year><Month>4</Month><Day>9</Day><Hour>0</Hour><Minute>1</Minute></PubMedPubDate><PubMedPubDate PubStatus="entrez"><Year>1999</Year><Month>4</Month><Day>9</Day><Hour>0</Hour><Minute>0</Minute></PubMedPubDate></History><PublicationStatus>ppublish</PublicationStatus><ArticleIdList><ArticleId IdType="pubmed">10195063</ArticleId></ArticleIdList></PubmedData></PubmedArticle></PubmedArticleSet>'